MANIFEST.in
README.asciidoc
setup.py
doc_crawler/__init__.py
doc_crawler/__main__.py
doc_crawler/doc_crawler.py
doc_crawler.egg-info/PKG-INFO
doc_crawler.egg-info/SOURCES.txt
doc_crawler.egg-info/dependency_links.txt
doc_crawler.egg-info/top_level.txt
doc_crawler/test/test_a.txt
doc_crawler/test/test_b.txt
doc_crawler/test/test_c.txt
doc_crawler/test/test_doc.lst