Metadata-Version: 1.2
Name: doc-crawler
Version: 1.2
Summary: Explore a website recursively and download all the wanted documents (PDF, ODT…)
Home-page: https://github.com/Siltaar/doc_crawler.py
Author: Simon Descarpentries
Author-email: contact@acoeuro.com
License: UNKNOWN
Keywords: crawler downloader recursive pdf-extractor web-crawler web-crawler-python file-download pdf zip doc odt
Platform: UNKNOWN
Classifier: Development Status :: 5 - Production/Stable
Classifier: Programming Language :: Python :: 3
Classifier: Operating System :: OS Independent
Classifier: Topic :: Internet :: WWW/HTTP
Classifier: Intended Audience :: End Users/Desktop
Classifier: Intended Audience :: Developers
Classifier: License :: OSI Approved :: GNU General Public License v3 or later (GPLv3+)
Requires-Python: >=3
